{
    "VPlayer": {
        "checkpoints": [
            {
                "steps": 7499995,
                "file_path": "results\\VPlayer-FirstButCorrected\\VPlayer\\VPlayer-7499995.onnx",
                "reward": -4.701355669487036,
                "creation_time": 1611382688.8984973
            },
            {
                "steps": 7917728,
                "file_path": "results\\VPlayer-FirstButCorrected\\VPlayer\\VPlayer-7917728.onnx",
                "reward": -4.290835876119101,
                "creation_time": 1611388998.116728
            },
            {
                "steps": 7999990,
                "file_path": "results\\VPlayer-FirstButCorrected\\VPlayer\\VPlayer-7999990.onnx",
                "reward": -3.1538095474243164,
                "creation_time": 1611390422.4662416
            },
            {
                "steps": 8372152,
                "file_path": "results\\VPlayer-FirstButCorrected\\VPlayer\\VPlayer-8372152.onnx",
                "reward": -4.289834336464449,
                "creation_time": 1611399289.6209278
            },
            {
                "steps": 8443610,
                "file_path": "results\\VPlayer-FirstButCorrected\\VPlayer\\VPlayer-8443610.onnx",
                "reward": -5.176262674354661,
                "creation_time": 1611404882.8449876
            }
        ],
        "final_checkpoint": {
            "steps": 8443610,
            "file_path": "results\\VPlayer-FirstButCorrected\\VPlayer.onnx",
            "reward": -5.176262674354661,
            "creation_time": 1611404882.8449876
        }
    },
    "metadata": {
        "stats_format_version": "0.2.0",
        "mlagents_version": "0.23.0",
        "torch_version": "1.7.0+cu110",
        "tensorflow_version": -1
    }
}